django_openid_auth/__init__.py
django_openid_auth/admin.py
django_openid_auth/auth.py
django_openid_auth/exceptions.py
django_openid_auth/forms.py
django_openid_auth/models.py
django_openid_auth/signals.py
django_openid_auth/store.py
django_openid_auth/teams.py
django_openid_auth/urls.py
django_openid_auth/views.py
django_openid_auth/management/__init__.py
django_openid_auth/management/commands/__init__.py
django_openid_auth/management/commands/openid_cleanup.py
django_openid_auth/migrations/0001_initial.py
django_openid_auth/migrations/__init__.py
django_openid_auth/templates/openid/failure.html
django_openid_auth/templates/openid/login.html
django_openid_auth/tests/__init__.py
django_openid_auth/tests/helpers.py
django_openid_auth/tests/models.py
django_openid_auth/tests/test_admin.py
django_openid_auth/tests/test_auth.py
django_openid_auth/tests/test_models.py
django_openid_auth/tests/test_settings.py
django_openid_auth/tests/test_store.py
django_openid_auth/tests/test_views.py
django_openid_auth/tests/urls.py
example_consumer/__init__.py
example_consumer/settings.py
example_consumer/urls.py
example_consumer/views.py
example_consumer/wsgi.py
django_openid_auth-0.17.dist-info/LICENSE.txt
django_openid_auth-0.17.dist-info/METADATA
django_openid_auth-0.17.dist-info/WHEEL
django_openid_auth-0.17.dist-info/top_level.txt
django_openid_auth-0.17.dist-info/RECORD
