Metadata-Version: 2.1
Name: django-openid-auth
Version: 0.17
Summary: OpenID integration for django.contrib.auth
Home-page: https://launchpad.net/django-openid-auth
Download-URL: http://launchpad.net/django-openid-auth/trunk/0.17/+download/django-openid-auth-0.17.tar.gz
Author: Canonical Ltd
Author-email: noreply@canonical.com
License: BSD
Platform: any
Classifier: Development Status :: 5 - Production/Stable
Classifier: Environment :: Web Environment
Classifier: Framework :: Django
Classifier: Intended Audience :: Developers
Classifier: License :: OSI Approved :: BSD License
Classifier: Operating System :: OS Independent
Classifier: Programming Language :: Python
Classifier: Topic :: Software Development :: Libraries :: Python Modules
License-File: LICENSE.txt
Requires-Dist: django (>=2.2)
Requires-Dist: python3-openid
